datamodelutils/__init__.py
datamodelutils/models.py
datamodelutils/postgres_admin.py
datamodelutils/repl.py
datamodelutils/validators.py
datamodelutils-1.2.0.dist-info/METADATA
datamodelutils-1.2.0.dist-info/WHEEL
datamodelutils-1.2.0.dist-info/entry_points.txt
datamodelutils-1.2.0.dist-info/licenses/LICENSE
datamodelutils-1.2.0.dist-info/licenses/NOTICE
datamodelutils-1.2.0.dist-info/RECORD
