Metadata-Version: 2.4
Name: datamodelutils
Version: 1.2.0
Summary: Gen3 Data Model Utils
License: Apache-2.0
License-File: LICENSE
License-File: NOTICE
Author: CTDS UChicago
Author-email: cdis@uchicago.edu
Requires-Python: >=3.13,<4
Classifier: License :: OSI Approved :: Apache Software License
Classifier: Programming Language :: Python :: 3
Classifier: Programming Language :: Python :: 3.13
Classifier: Programming Language :: Python :: 3.14
Provides-Extra: ipython
Requires-Dist: dictionaryutils (>=3)
Requires-Dist: gen3datamodel (>=3)
Requires-Dist: ipython ; extra == "ipython"
Requires-Dist: psqlgraph
Requires-Dist: sqlalchemy (<3)
Project-URL: Repository, https://github.com/uc-cdis/datamodelutils
